<report>
  <ID>29985a5f-e8e8-4480-9134-1a611c2ccb1d</ID>
  <name>
    <first_name>Gary</first_name>
    <last_name>Abbott</last_name>
  </name>
  <SSN>087-39-4777</SSN>
  <address>81170 Hicks Isle
Evansville, MD 71670</address>
  <score>1740</score>
  <tradelines>
    <tradeline>
      <type>REVOLVING</type>
      <last_activity>2012</last_activity>
      <high_credit>2799</high_credit>
      <balance>0</balance>
      <active>False</active>
      <status>PAID</status>
      <payments>
        <payment>
          <month>1</month>
          <status>30 DAYS LATE</status>
        </payment>
        <payment>
          <month>2</month>
          <status>ON TIME</status>
        </payment>
        <payment>
          <month>3</month>
          <status>ON TIME</status>
        </payment>
        <payment>
          <month>4</month>
          <status>ON TIME</status>
        </payment>
        <payment>
          <month>5</month>
          <status>ON TIME</status>
        </payment>
        <payment>
          <month>6</month>
          <status>ON TIME</status>
        </payment>
        <payment>
          <month>7</month>
          <status>ON TIME</status>
        </payment>
        <payment>
          <month>8</month>
          <status>ON TIME</status>
        </payment>
        <payment>
          <month>9</month>
          <status>ON TIME</status>
        </payment>
      </payments>
    </tradeline>
    <tradeline>
      <type>AUTO</type>
      <last_activity>2004</last_activity>
      <high_credit>15942</high_credit>
      <balance>0</balance>
      <active>False</active>
      <status>PAID</status>
      <payments>
        <payment>
          <month>1</month>
          <status>ON TIME</status>
        </payment>
        <payment>
          <month>2</month>
          <status>ON TIME</status>
        </payment>
        <payment>
          <month>3</month>
          <status>ON TIME</status>
        </payment>
        <payment>
          <month>4</month>
          <status>ON TIME</status>
        </payment>
        <payment>
          <month>5</month>
          <status>ON TIME</status>
        </payment>
        <payment>
          <month>6</month>
          <status>ON TIME</status>
        </payment>
        <payment>
          <month>7</month>
          <status>ON TIME</status>
        </payment>
        <payment>
          <month>8</month>
          <status>ON TIME</status>
        </payment>
        <payment>
          <month>9</month>
          <status>ON TIME</status>
        </payment>
        <payment>
          <month>10</month>
          <status>ON TIME</status>
        </payment>
        <payment>
          <month>11</month>
          <status>ON TIME</status>
        </payment>
        <payment>
          <month>12</month>
          <status>60 DAYS LATE OR MORE</status>
        </payment>
        <payment>
          <month>13</month>
          <status>ON TIME</status>
        </payment>
        <payment>
          <month>14</month>
          <status>ON TIME</status>
        </payment>
        <payment>
          <month>15</month>
          <status>ON TIME</status>
        </payment>
        <payment>
          <month>16</month>
          <status>ON TIME</status>
        </payment>
        <payment>
          <month>17</month>
          <status>ON TIME</status>
        </payment>
        <payment>
          <month>18</month>
          <status>ON TIME</status>
        </payment>
        <payment>
          <month>19</month>
          <status>ON TIME</status>
        </payment>
        <payment>
          <month>20</month>
          <status>ON TIME</status>
        </payment>
        <payment>
          <month>21</month>
          <status>ON TIME</status>
        </payment>
        <payment>
          <month>22</month>
          <status>ON TIME</status>
        </payment>
        <payment>
          <month>23</month>
          <status>ON TIME</status>
        </payment>
        <payment>
          <month>24</month>
          <status>ON TIME</status>
        </payment>
        <payment>
          <month>25</month>
          <status>ON TIME</status>
        </payment>
        <payment>
          <month>26</month>
          <status>ON TIME</status>
        </payment>
        <payment>
          <month>27</month>
          <status>ON TIME</status>
        </payment>
        <payment>
          <month>28</month>
          <status>ON TIME</status>
        </payment>
      </payments>
    </tradeline>
    <tradeline>
      <type>AUTO</type>
      <last_activity>2018</last_activity>
      <high_credit>19846</high_credit>
      <balance>0</balance>
      <active>False</active>
      <status>PAID</status>
      <payments>
        <payment>
          <month>1</month>
          <status>ON TIME</status>
        </payment>
        <payment>
          <month>2</month>
          <status>ON TIME</status>
        </payment>
        <payment>
          <month>3</month>
          <status>ON TIME</status>
        </payment>
        <payment>
          <month>4</month>
          <status>ON TIME</status>
        </payment>
        <payment>
          <month>5</month>
          <status>ON TIME</status>
        </payment>
        <payment>
          <month>6</month>
          <status>ON TIME</status>
        </payment>
        <payment>
          <month>7</month>
          <status>ON TIME</status>
        </payment>
        <payment>
          <month>8</month>
          <status>ON TIME</status>
        </payment>
        <payment>
          <month>9</month>
          <status>ON TIME</status>
        </payment>
      </payments>
    </tradeline>
    <tradeline>
      <type>EDU</type>
      <last_activity>2003</last_activity>
      <high_credit>12622</high_credit>
      <balance>0</balance>
      <active>False</active>
      <status>PAID</status>
      <payments>
        <payment>
          <month>1</month>
          <status>ON TIME</status>
        </payment>
        <payment>
          <month>2</month>
          <status>ON TIME</status>
        </payment>
        <payment>
          <month>3</month>
          <status>ON TIME</status>
        </payment>
        <payment>
          <month>4</month>
          <status>ON TIME</status>
        </payment>
        <payment>
          <month>5</month>
          <status>ON TIME</status>
        </payment>
        <payment>
          <month>6</month>
          <status>ON TIME</status>
        </payment>
        <payment>
          <month>7</month>
          <status>60 DAYS LATE OR MORE</status>
        </payment>
        <payment>
          <month>8</month>
          <status>ON TIME</status>
        </payment>
      </payments>
    </tradeline>
    <tradeline>
      <type>REVOLVING</type>
      <last_activity>2000</last_activity>
      <high_credit>10890</high_credit>
      <balance>0</balance>
      <active>False</active>
      <status>PAID</status>
      <payments>
        <payment>
          <month>1</month>
          <status>ON TIME</status>
        </payment>
        <payment>
          <month>2</month>
          <status>ON TIME</status>
        </payment>
        <payment>
          <month>3</month>
          <status>ON TIME</status>
        </payment>
        <payment>
          <month>4</month>
          <status>60 DAYS LATE OR MORE</status>
        </payment>
        <payment>
          <month>5</month>
          <status>ON TIME</status>
        </payment>
        <payment>
          <month>6</month>
          <status>ON TIME</status>
        </payment>
        <payment>
          <month>7</month>
          <status>ON TIME</status>
        </payment>
        <payment>
          <month>8</month>
          <status>ON TIME</status>
        </payment>
        <payment>
          <month>9</month>
          <status>ON TIME</status>
        </payment>
        <payment>
          <month>10</month>
          <status>ON TIME</status>
        </payment>
        <payment>
          <month>11</month>
          <status>ON TIME</status>
        </payment>
        <payment>
          <month>12</month>
          <status>ON TIME</status>
        </payment>
        <payment>
          <month>13</month>
          <status>ON TIME</status>
        </payment>
        <payment>
          <month>14</month>
          <status>ON TIME</status>
        </payment>
        <payment>
          <month>15</month>
          <status>30 DAYS LATE</status>
        </payment>
        <payment>
          <month>16</month>
          <status>60 DAYS LATE OR MORE</status>
        </payment>
        <payment>
          <month>17</month>
          <status>ON TIME</status>
        </payment>
        <payment>
          <month>18</month>
          <status>ON TIME</status>
        </payment>
      </payments>
    </tradeline>
    <tradeline>
      <type>AUTO</type>
      <last_activity>2011</last_activity>
      <high_credit>3029</high_credit>
      <balance>0</balance>
      <active>False</active>
      <status>PAID</status>
      <payments>
        <payment>
          <month>1</month>
          <status>ON TIME</status>
        </payment>
        <payment>
          <month>2</month>
          <status>ON TIME</status>
        </payment>
        <payment>
          <month>3</month>
          <status>ON TIME</status>
        </payment>
        <payment>
          <month>4</month>
          <status>ON TIME</status>
        </payment>
        <payment>
          <month>5</month>
          <status>30 DAYS LATE</status>
        </payment>
        <payment>
          <month>6</month>
          <status>30 DAYS LATE</status>
        </payment>
        <payment>
          <month>7</month>
          <status>ON TIME</status>
        </payment>
        <payment>
          <month>8</month>
          <status>ON TIME</status>
        </payment>
        <payment>
          <month>9</month>
          <status>ON TIME</status>
        </payment>
        <payment>
          <month>10</month>
          <status>ON TIME</status>
        </payment>
        <payment>
          <month>11</month>
          <status>ON TIME</status>
        </payment>
        <payment>
          <month>12</month>
          <status>ON TIME</status>
        </payment>
        <payment>
          <month>13</month>
          <status>ON TIME</status>
        </payment>
      </payments>
    </tradeline>
    <tradeline>
      <type>REVOLVING</type>
      <last_activity>2013</last_activity>
      <high_credit>19053</high_credit>
      <balance>12178</balance>
      <active>False</active>
      <status>COLLECTIONS</status>
      <payments>
        <payment>
          <month>1</month>
          <status>ON TIME</status>
        </payment>
        <payment>
          <month>2</month>
          <status>ON TIME</status>
        </payment>
        <payment>
          <month>3</month>
          <status>ON TIME</status>
        </payment>
        <payment>
          <month>4</month>
          <status>ON TIME</status>
        </payment>
        <payment>
          <month>5</month>
          <status>ON TIME</status>
        </payment>
        <payment>
          <month>6</month>
          <status>ON TIME</status>
        </payment>
        <payment>
          <month>7</month>
          <status>ON TIME</status>
        </payment>
        <payment>
          <month>8</month>
          <status>ON TIME</status>
        </payment>
        <payment>
          <month>9</month>
          <status>ON TIME</status>
        </payment>
        <payment>
          <month>10</month>
          <status>ON TIME</status>
        </payment>
        <payment>
          <month>11</month>
          <status>ON TIME</status>
        </payment>
        <payment>
          <month>12</month>
          <status>30 DAYS LATE</status>
        </payment>
        <payment>
          <month>13</month>
          <status>60 DAYS LATE OR MORE</status>
        </payment>
        <payment>
          <month>14</month>
          <status>ON TIME</status>
        </payment>
        <payment>
          <month>15</month>
          <status>ON TIME</status>
        </payment>
        <payment>
          <month>16</month>
          <status>ON TIME</status>
        </payment>
        <payment>
          <month>17</month>
          <status>ON TIME</status>
        </payment>
        <payment>
          <month>18</month>
          <status>ON TIME</status>
        </payment>
        <payment>
          <month>19</month>
          <status>60 DAYS LATE OR MORE</status>
        </payment>
      </payments>
    </tradeline>
    <tradeline>
      <type>EDU</type>
      <last_activity>2013</last_activity>
      <high_credit>7722</high_credit>
      <balance>0</balance>
      <active>False</active>
      <status>PAID</status>
      <payments>
        <payment>
          <month>1</month>
          <status>ON TIME</status>
        </payment>
        <payment>
          <month>2</month>
          <status>ON TIME</status>
        </payment>
        <payment>
          <month>3</month>
          <status>ON TIME</status>
        </payment>
        <payment>
          <month>4</month>
          <status>ON TIME</status>
        </payment>
        <payment>
          <month>5</month>
          <status>ON TIME</status>
        </payment>
        <payment>
          <month>6</month>
          <status>ON TIME</status>
        </payment>
        <payment>
          <month>7</month>
          <status>60 DAYS LATE OR MORE</status>
        </payment>
        <payment>
          <month>8</month>
          <status>ON TIME</status>
        </payment>
        <payment>
          <month>9</month>
          <status>60 DAYS LATE OR MORE</status>
        </payment>
        <payment>
          <month>10</month>
          <status>ON TIME</status>
        </payment>
        <payment>
          <month>11</month>
          <status>ON TIME</status>
        </payment>
        <payment>
          <month>12</month>
          <status>ON TIME</status>
        </payment>
        <payment>
          <month>13</month>
          <status>ON TIME</status>
        </payment>
        <payment>
          <month>14</month>
          <status>ON TIME</status>
        </payment>
        <payment>
          <month>15</month>
          <status>ON TIME</status>
        </payment>
        <payment>
          <month>16</month>
          <status>ON TIME</status>
        </payment>
        <payment>
          <month>17</month>
          <status>30 DAYS LATE</status>
        </payment>
        <payment>
          <month>18</month>
          <status>ON TIME</status>
        </payment>
        <payment>
          <month>19</month>
          <status>ON TIME</status>
        </payment>
        <payment>
          <month>20</month>
          <status>ON TIME</status>
        </payment>
        <payment>
          <month>21</month>
          <status>ON TIME</status>
        </payment>
        <payment>
          <month>22</month>
          <status>ON TIME</status>
        </payment>
        <payment>
          <month>23</month>
          <status>ON TIME</status>
        </payment>
        <payment>
          <month>24</month>
          <status>ON TIME</status>
        </payment>
        <payment>
          <month>25</month>
          <status>ON TIME</status>
        </payment>
        <payment>
          <month>26</month>
          <status>ON TIME</status>
        </payment>
        <payment>
          <month>27</month>
          <status>ON TIME</status>
        </payment>
        <payment>
          <month>28</month>
          <status>ON TIME</status>
        </payment>
        <payment>
          <month>29</month>
          <status>60 DAYS LATE OR MORE</status>
        </payment>
        <payment>
          <month>30</month>
          <status>ON TIME</status>
        </payment>
        <payment>
          <month>31</month>
          <status>ON TIME</status>
        </payment>
        <payment>
          <month>32</month>
          <status>ON TIME</status>
        </payment>
        <payment>
          <month>33</month>
          <status>ON TIME</status>
        </payment>
        <payment>
          <month>34</month>
          <status>ON TIME</status>
        </payment>
        <payment>
          <month>35</month>
          <status>ON TIME</status>
        </payment>
        <payment>
          <month>36</month>
          <status>ON TIME</status>
        </payment>
      </payments>
    </tradeline>
    <tradeline>
      <type>AUTO</type>
      <last_activity>2002</last_activity>
      <high_credit>11943</high_credit>
      <balance>0</balance>
      <active>False</active>
      <status>PAID</status>
      <payments>
        <payment>
          <month>1</month>
          <status>30 DAYS LATE</status>
        </payment>
        <payment>
          <month>2</month>
          <status>ON TIME</status>
        </payment>
        <payment>
          <month>3</month>
          <status>ON TIME</status>
        </payment>
        <payment>
          <month>4</month>
          <status>ON TIME</status>
        </payment>
        <payment>
          <month>5</month>
          <status>ON TIME</status>
        </payment>
        <payment>
          <month>6</month>
          <status>ON TIME</status>
        </payment>
        <payment>
          <month>7</month>
          <status>ON TIME</status>
        </payment>
        <payment>
          <month>8</month>
          <status>ON TIME</status>
        </payment>
        <payment>
          <month>9</month>
          <status>ON TIME</status>
        </payment>
        <payment>
          <month>10</month>
          <status>ON TIME</status>
        </payment>
        <payment>
          <month>11</month>
          <status>ON TIME</status>
        </payment>
        <payment>
          <month>12</month>
          <status>30 DAYS LATE</status>
        </payment>
        <payment>
          <month>13</month>
          <status>ON TIME</status>
        </payment>
        <payment>
          <month>14</month>
          <status>ON TIME</status>
        </payment>
        <payment>
          <month>15</month>
          <status>ON TIME</status>
        </payment>
        <payment>
          <month>16</month>
          <status>30 DAYS LATE</status>
        </payment>
        <payment>
          <month>17</month>
          <status>ON TIME</status>
        </payment>
        <payment>
          <month>18</month>
          <status>ON TIME</status>
        </payment>
        <payment>
          <month>19</month>
          <status>ON TIME</status>
        </payment>
        <payment>
          <month>20</month>
          <status>ON TIME</status>
        </payment>
        <payment>
          <month>21</month>
          <status>30 DAYS LATE</status>
        </payment>
        <payment>
          <month>22</month>
          <status>ON TIME</status>
        </payment>
        <payment>
          <month>23</month>
          <status>ON TIME</status>
        </payment>
        <payment>
          <month>24</month>
          <status>ON TIME</status>
        </payment>
        <payment>
          <month>25</month>
          <status>ON TIME</status>
        </payment>
        <payment>
          <month>26</month>
          <status>ON TIME</status>
        </payment>
        <payment>
          <month>27</month>
          <status>ON TIME</status>
        </payment>
        <payment>
          <month>28</month>
          <status>ON TIME</status>
        </payment>
        <payment>
          <month>29</month>
          <status>30 DAYS LATE</status>
        </payment>
        <payment>
          <month>30</month>
          <status>60 DAYS LATE OR MORE</status>
        </payment>
        <payment>
          <month>31</month>
          <status>ON TIME</status>
        </payment>
        <payment>
          <month>32</month>
          <status>ON TIME</status>
        </payment>
        <payment>
          <month>33</month>
          <status>ON TIME</status>
        </payment>
        <payment>
          <month>34</month>
          <status>ON TIME</status>
        </payment>
        <payment>
          <month>35</month>
          <status>ON TIME</status>
        </payment>
        <payment>
          <month>36</month>
          <status>ON TIME</status>
        </payment>
        <payment>
          <month>37</month>
          <status>ON TIME</status>
        </payment>
        <payment>
          <month>38</month>
          <status>ON TIME</status>
        </payment>
        <payment>
          <month>39</month>
          <status>60 DAYS LATE OR MORE</status>
        </payment>
        <payment>
          <month>40</month>
          <status>ON TIME</status>
        </payment>
      </payments>
    </tradeline>
    <tradeline>
      <type>AUTO</type>
      <last_activity>2020</last_activity>
      <high_credit>15736</high_credit>
      <balance>12102</balance>
      <active>True</active>
      <status>CURRENT</status>
      <payments>
        <payment>
          <month>1</month>
          <status>ON TIME</status>
        </payment>
        <payment>
          <month>2</month>
          <status>ON TIME</status>
        </payment>
        <payment>
          <month>3</month>
          <status>ON TIME</status>
        </payment>
        <payment>
          <month>4</month>
          <status>ON TIME</status>
        </payment>
        <payment>
          <month>5</month>
          <status>ON TIME</status>
        </payment>
        <payment>
          <month>6</month>
          <status>ON TIME</status>
        </payment>
        <payment>
          <month>7</month>
          <status>ON TIME</status>
        </payment>
        <payment>
          <month>8</month>
          <status>ON TIME</status>
        </payment>
        <payment>
          <month>9</month>
          <status>ON TIME</status>
        </payment>
        <payment>
          <month>10</month>
          <status>ON TIME</status>
        </payment>
        <payment>
          <month>11</month>
          <status>ON TIME</status>
        </payment>
        <payment>
          <month>12</month>
          <status>ON TIME</status>
        </payment>
        <payment>
          <month>13</month>
          <status>ON TIME</status>
        </payment>
        <payment>
          <month>14</month>
          <status>30 DAYS LATE</status>
        </payment>
        <payment>
          <month>15</month>
          <status>ON TIME</status>
        </payment>
        <payment>
          <month>16</month>
          <status>ON TIME</status>
        </payment>
        <payment>
          <month>17</month>
          <status>ON TIME</status>
        </payment>
        <payment>
          <month>18</month>
          <status>ON TIME</status>
        </payment>
        <payment>
          <month>19</month>
          <status>30 DAYS LATE</status>
        </payment>
        <payment>
          <month>20</month>
          <status>ON TIME</status>
        </payment>
      </payments>
    </tradeline>
    <tradeline>
      <type>REVOLVING</type>
      <last_activity>2020</last_activity>
      <high_credit>15680</high_credit>
      <balance>6283</balance>
      <active>True</active>
      <status>CURRENT</status>
      <payments>
        <payment>
          <month>1</month>
          <status>ON TIME</status>
        </payment>
        <payment>
          <month>2</month>
          <status>ON TIME</status>
        </payment>
        <payment>
          <month>3</month>
          <status>ON TIME</status>
        </payment>
        <payment>
          <month>4</month>
          <status>ON TIME</status>
        </payment>
        <payment>
          <month>5</month>
          <status>ON TIME</status>
        </payment>
      </payments>
    </tradeline>
    <tradeline>
      <type>EDU</type>
      <last_activity>2020</last_activity>
      <high_credit>19246</high_credit>
      <balance>21927</balance>
      <active>True</active>
      <status>CURRENT</status>
      <payments>
        <payment>
          <month>1</month>
          <status>ON TIME</status>
        </payment>
        <payment>
          <month>2</month>
          <status>ON TIME</status>
        </payment>
        <payment>
          <month>3</month>
          <status>ON TIME</status>
        </payment>
        <payment>
          <month>4</month>
          <status>ON TIME</status>
        </payment>
        <payment>
          <month>5</month>
          <status>ON TIME</status>
        </payment>
        <payment>
          <month>6</month>
          <status>60 DAYS LATE OR MORE</status>
        </payment>
        <payment>
          <month>7</month>
          <status>ON TIME</status>
        </payment>
        <payment>
          <month>8</month>
          <status>60 DAYS LATE OR MORE</status>
        </payment>
        <payment>
          <month>9</month>
          <status>ON TIME</status>
        </payment>
        <payment>
          <month>10</month>
          <status>ON TIME</status>
        </payment>
        <payment>
          <month>11</month>
          <status>ON TIME</status>
        </payment>
        <payment>
          <month>12</month>
          <status>ON TIME</status>
        </payment>
        <payment>
          <month>13</month>
          <status>ON TIME</status>
        </payment>
        <payment>
          <month>14</month>
          <status>ON TIME</status>
        </payment>
        <payment>
          <month>15</month>
          <status>ON TIME</status>
        </payment>
        <payment>
          <month>16</month>
          <status>ON TIME</status>
        </payment>
      </payments>
    </tradeline>
    <tradeline>
      <type>REVOLVING</type>
      <last_activity>2020</last_activity>
      <high_credit>5924</high_credit>
      <balance>3607</balance>
      <active>True</active>
      <status>CURRENT</status>
      <payments>
        <payment>
          <month>1</month>
          <status>30 DAYS LATE</status>
        </payment>
        <payment>
          <month>2</month>
          <status>ON TIME</status>
        </payment>
        <payment>
          <month>3</month>
          <status>ON TIME</status>
        </payment>
        <payment>
          <month>4</month>
          <status>ON TIME</status>
        </payment>
        <payment>
          <month>5</month>
          <status>ON TIME</status>
        </payment>
        <payment>
          <month>6</month>
          <status>ON TIME</status>
        </payment>
      </payments>
    </tradeline>
    <tradeline>
      <type>REVOLVING</type>
      <last_activity>2020</last_activity>
      <high_credit>5942</high_credit>
      <balance>4871</balance>
      <active>True</active>
      <status>CURRENT</status>
      <payments>
        <payment>
          <month>1</month>
          <status>ON TIME</status>
        </payment>
        <payment>
          <month>2</month>
          <status>30 DAYS LATE</status>
        </payment>
        <payment>
          <month>3</month>
          <status>ON TIME</status>
        </payment>
        <payment>
          <month>4</month>
          <status>ON TIME</status>
        </payment>
        <payment>
          <month>5</month>
          <status>ON TIME</status>
        </payment>
        <payment>
          <month>6</month>
          <status>ON TIME</status>
        </payment>
        <payment>
          <month>7</month>
          <status>60 DAYS LATE OR MORE</status>
        </payment>
        <payment>
          <month>8</month>
          <status>ON TIME</status>
        </payment>
        <payment>
          <month>9</month>
          <status>ON TIME</status>
        </payment>
        <payment>
          <month>10</month>
          <status>ON TIME</status>
        </payment>
        <payment>
          <month>11</month>
          <status>ON TIME</status>
        </payment>
        <payment>
          <month>12</month>
          <status>ON TIME</status>
        </payment>
        <payment>
          <month>13</month>
          <status>ON TIME</status>
        </payment>
        <payment>
          <month>14</month>
          <status>ON TIME</status>
        </payment>
        <payment>
          <month>15</month>
          <status>ON TIME</status>
        </payment>
        <payment>
          <month>16</month>
          <status>ON TIME</status>
        </payment>
        <payment>
          <month>17</month>
          <status>ON TIME</status>
        </payment>
        <payment>
          <month>18</month>
          <status>ON TIME</status>
        </payment>
        <payment>
          <month>19</month>
          <status>ON TIME</status>
        </payment>
        <payment>
          <month>20</month>
          <status>ON TIME</status>
        </payment>
        <payment>
          <month>21</month>
          <status>ON TIME</status>
        </payment>
        <payment>
          <month>22</month>
          <status>ON TIME</status>
        </payment>
        <payment>
          <month>23</month>
          <status>60 DAYS LATE OR MORE</status>
        </payment>
        <payment>
          <month>24</month>
          <status>30 DAYS LATE</status>
        </payment>
        <payment>
          <month>25</month>
          <status>ON TIME</status>
        </payment>
        <payment>
          <month>26</month>
          <status>ON TIME</status>
        </payment>
        <payment>
          <month>27</month>
          <status>ON TIME</status>
        </payment>
        <payment>
          <month>28</month>
          <status>ON TIME</status>
        </payment>
        <payment>
          <month>29</month>
          <status>ON TIME</status>
        </payment>
        <payment>
          <month>30</month>
          <status>ON TIME</status>
        </payment>
      </payments>
    </tradeline>
    <tradeline>
      <type>AUTO</type>
      <last_activity>2020</last_activity>
      <high_credit>13927</high_credit>
      <balance>13502</balance>
      <active>True</active>
      <status>CURRENT</status>
      <payments>
        <payment>
          <month>1</month>
          <status>ON TIME</status>
        </payment>
        <payment>
          <month>2</month>
          <status>ON TIME</status>
        </payment>
        <payment>
          <month>3</month>
          <status>60 DAYS LATE OR MORE</status>
        </payment>
        <payment>
          <month>4</month>
          <status>ON TIME</status>
        </payment>
        <payment>
          <month>5</month>
          <status>ON TIME</status>
        </payment>
        <payment>
          <month>6</month>
          <status>ON TIME</status>
        </payment>
        <payment>
          <month>7</month>
          <status>ON TIME</status>
        </payment>
        <payment>
          <month>8</month>
          <status>ON TIME</status>
        </payment>
        <payment>
          <month>9</month>
          <status>ON TIME</status>
        </payment>
        <payment>
          <month>10</month>
          <status>ON TIME</status>
        </payment>
        <payment>
          <month>11</month>
          <status>ON TIME</status>
        </payment>
      </payments>
    </tradeline>
    <tradeline>
      <type>REVOLVING</type>
      <last_activity>2020</last_activity>
      <high_credit>12915</high_credit>
      <balance>6859</balance>
      <active>True</active>
      <status>CURRENT</status>
      <payments>
        <payment>
          <month>1</month>
          <status>ON TIME</status>
        </payment>
        <payment>
          <month>2</month>
          <status>ON TIME</status>
        </payment>
        <payment>
          <month>3</month>
          <status>ON TIME</status>
        </payment>
        <payment>
          <month>4</month>
          <status>ON TIME</status>
        </payment>
        <payment>
          <month>5</month>
          <status>ON TIME</status>
        </payment>
        <payment>
          <month>6</month>
          <status>60 DAYS LATE OR MORE</status>
        </payment>
        <payment>
          <month>7</month>
          <status>ON TIME</status>
        </payment>
        <payment>
          <month>8</month>
          <status>ON TIME</status>
        </payment>
        <payment>
          <month>9</month>
          <status>ON TIME</status>
        </payment>
        <payment>
          <month>10</month>
          <status>ON TIME</status>
        </payment>
        <payment>
          <month>11</month>
          <status>ON TIME</status>
        </payment>
        <payment>
          <month>12</month>
          <status>ON TIME</status>
        </payment>
        <payment>
          <month>13</month>
          <status>ON TIME</status>
        </payment>
        <payment>
          <month>14</month>
          <status>ON TIME</status>
        </payment>
        <payment>
          <month>15</month>
          <status>ON TIME</status>
        </payment>
        <payment>
          <month>16</month>
          <status>ON TIME</status>
        </payment>
        <payment>
          <month>17</month>
          <status>ON TIME</status>
        </payment>
        <payment>
          <month>18</month>
          <status>ON TIME</status>
        </payment>
        <payment>
          <month>19</month>
          <status>ON TIME</status>
        </payment>
        <payment>
          <month>20</month>
          <status>ON TIME</status>
        </payment>
        <payment>
          <month>21</month>
          <status>ON TIME</status>
        </payment>
        <payment>
          <month>22</month>
          <status>ON TIME</status>
        </payment>
        <payment>
          <month>23</month>
          <status>ON TIME</status>
        </payment>
        <payment>
          <month>24</month>
          <status>ON TIME</status>
        </payment>
        <payment>
          <month>25</month>
          <status>ON TIME</status>
        </payment>
        <payment>
          <month>26</month>
          <status>ON TIME</status>
        </payment>
        <payment>
          <month>27</month>
          <status>ON TIME</status>
        </payment>
        <payment>
          <month>28</month>
          <status>ON TIME</status>
        </payment>
        <payment>
          <month>29</month>
          <status>ON TIME</status>
        </payment>
        <payment>
          <month>30</month>
          <status>ON TIME</status>
        </payment>
        <payment>
          <month>31</month>
          <status>ON TIME</status>
        </payment>
        <payment>
          <month>32</month>
          <status>ON TIME</status>
        </payment>
        <payment>
          <month>33</month>
          <status>ON TIME</status>
        </payment>
      </payments>
    </tradeline>
    <tradeline>
      <type>AUTO</type>
      <last_activity>2020</last_activity>
      <high_credit>11564</high_credit>
      <balance>4959</balance>
      <active>True</active>
      <status>CURRENT</status>
      <payments>
        <payment>
          <month>1</month>
          <status>ON TIME</status>
        </payment>
        <payment>
          <month>2</month>
          <status>ON TIME</status>
        </payment>
        <payment>
          <month>3</month>
          <status>ON TIME</status>
        </payment>
        <payment>
          <month>4</month>
          <status>30 DAYS LATE</status>
        </payment>
        <payment>
          <month>5</month>
          <status>ON TIME</status>
        </payment>
        <payment>
          <month>6</month>
          <status>ON TIME</status>
        </payment>
        <payment>
          <month>7</month>
          <status>ON TIME</status>
        </payment>
        <payment>
          <month>8</month>
          <status>30 DAYS LATE</status>
        </payment>
        <payment>
          <month>9</month>
          <status>ON TIME</status>
        </payment>
      </payments>
    </tradeline>
  </tradelines>
</report>
